uk_election_ids/__init__.py
uk_election_ids/datapackage.py
uk_election_ids/election_ids.py
uk_election_ids/metadata_tools.py
uk_election_ids/parser.py
uk_election_ids/slugger.py
uk_election_ids/data/id_requirements.json
uk_election_ids/data/postal_votes.json
uk_election_ids/data/voting_systems.json
uk_election_ids-0.10.0.dist-info/licenses/LICENSE
uk_election_ids-0.10.0.dist-info/METADATA
uk_election_ids-0.10.0.dist-info/WHEEL
uk_election_ids-0.10.0.dist-info/top_level.txt
uk_election_ids-0.10.0.dist-info/RECORD
