Metadata-Version: 2.4
Name: uk_election_ids
Version: 0.10.0
Summary: Create Democracy Club Election Identifiers
Home-page: https://github.com/DemocracyClub/uk-election-ids/
Author: chris48s
License: MIT
Project-URL: Documentation, https://democracyclub.github.io/uk-election-ids/
Project-URL: Source, https://github.com/DemocracyClub/uk-election-ids/
Classifier: License :: OSI Approved :: MIT License
Classifier: Programming Language :: Python
Classifier: Programming Language :: Python :: 3
Classifier: Programming Language :: Python :: 3.10
Classifier: Programming Language :: Python :: 3.11
Classifier: Programming Language :: Python :: 3.12
License-File: LICENSE
Provides-Extra: testing
Requires-Dist: coveralls; extra == "testing"
Provides-Extra: docs
Requires-Dist: sphinx==7.1.2; extra == "docs"
Requires-Dist: sphinx_rtd_theme==2.0.0; extra == "docs"
Requires-Dist: ghp-import==2.1.0; extra == "docs"
Provides-Extra: development
Requires-Dist: pydantic==1.10.18; extra == "development"
Requires-Dist: pre-commit==3.5.0; extra == "development"
Requires-Dist: ruff==0.3.7; extra == "development"
Dynamic: author
Dynamic: classifier
Dynamic: description
Dynamic: description-content-type
Dynamic: home-page
Dynamic: license
Dynamic: license-file
Dynamic: project-url
Dynamic: provides-extra
Dynamic: summary
